tokenterminal/__init__.py
tokenterminal/__version__.py
tokenterminal/tokenterminal.py
tokenterminal-2.0.0.dist-info/LICENSE
tokenterminal-2.0.0.dist-info/METADATA
tokenterminal-2.0.0.dist-info/WHEEL
tokenterminal-2.0.0.dist-info/top_level.txt
tokenterminal-2.0.0.dist-info/RECORD
